lobby/__init__.py
lobby/order.py
lobby/orderbook.py
lobby/orderlist.py
lobby/ordertree.py
lobby/version.py
lobby/bintree/__init__.py
lobby/bintree/iterator.py
lobby/bintree/rbtree.py
lobby/bintree/treemixin.py
lobby/bintree/treeslice.py
lobby/bintree/walker.py
lobby-0.1.3.dist-info/LICENSE.md
lobby-0.1.3.dist-info/METADATA
lobby-0.1.3.dist-info/WHEEL
lobby-0.1.3.dist-info/top_level.txt
lobby-0.1.3.dist-info/RECORD
