Metadata-Version: 2.1
Name: lobby
Version: 0.1.3
Summary: Simulate market and limit orders.
Home-page: https://github.com/mikedh/lobby
Author: Ash Booth, Michael Dawson-Haggerty
Author-email: mikedh@kerfed.com
License: MIT
Keywords: trading simulation market limit order
Platform: UNKNOWN
Classifier: Development Status :: 3 - Alpha
Classifier: License :: OSI Approved :: MIT License
Classifier: Programming Language :: Python
Classifier: Programming Language :: Python :: 2.7
Classifier: Programming Language :: Python :: 3.3
Classifier: Programming Language :: Python :: 3.4
Classifier: Programming Language :: Python :: 3.5
Classifier: Programming Language :: Python :: 3.6
Classifier: Programming Language :: Python :: 3.7
Classifier: Natural Language :: English
Classifier: Topic :: Scientific/Engineering
